setup_utility.py
jfaleiro.setup_utility-0.0.1.dist-info/LICENSE
jfaleiro.setup_utility-0.0.1.dist-info/METADATA
jfaleiro.setup_utility-0.0.1.dist-info/WHEEL
jfaleiro.setup_utility-0.0.1.dist-info/top_level.txt
jfaleiro.setup_utility-0.0.1.dist-info/RECORD
