Metadata-Version: 2.1
Name: jfaleiro.setup-utility
Version: 0.0.1
Summary: Shared helpers for setuptools configuration
Home-page: https://gitlab.com/jfaleiro/setup_utility
Author: Jorge M. Faleiro Jr.
Author-email: j@falei.ro
License: Affero GPL, see LICENSE for details
Download-URL: https://github.com/jfaleiro/setup_utility/tarball/master
Platform: UNKNOWN
Classifier: Programming Language :: Python
Classifier: Programming Language :: Python :: 3
Classifier: Development Status :: 4 - Beta
Classifier: Intended Audience :: Developers
Classifier: License :: OSI Approved :: GNU Affero General Public License v3
Classifier: Operating System :: OS Independent
Classifier: Topic :: Software Development
Classifier: Topic :: Software Development :: Libraries :: Python Modules
Requires-Dist: behave
Requires-Dist: nose (>=1.0)
Requires-Dist: coverage
Requires-Dist: mock
Requires-Dist: pytest-runner
Requires-Dist: pytest
Requires-Dist: PyHamcrest
